odoo/addons/purchase_order_product_recommendation/README.rst
odoo/addons/purchase_order_product_recommendation/__init__.py
odoo/addons/purchase_order_product_recommendation/__manifest__.py
odoo/addons/purchase_order_product_recommendation/i18n/es.po
odoo/addons/purchase_order_product_recommendation/i18n/purchase_order_product_recommendation.pot
odoo/addons/purchase_order_product_recommendation/readme/CONTRIBUTORS.rst
odoo/addons/purchase_order_product_recommendation/readme/DESCRIPTION.rst
odoo/addons/purchase_order_product_recommendation/readme/USAGE.rst
odoo/addons/purchase_order_product_recommendation/static/description/icon.png
odoo/addons/purchase_order_product_recommendation/static/description/index.html
odoo/addons/purchase_order_product_recommendation/tests/__init__.py
odoo/addons/purchase_order_product_recommendation/tests/test_recommendation.py
odoo/addons/purchase_order_product_recommendation/views/purchase_order_view.xml
odoo/addons/purchase_order_product_recommendation/wizards/__init__.py
odoo/addons/purchase_order_product_recommendation/wizards/purchase_order_recommendation.py
odoo/addons/purchase_order_product_recommendation/wizards/purchase_order_recommendation_view.xml
odoo13_addon_purchase_order_product_recommendation-13.0.1.1.0.dist-info/METADATA
odoo13_addon_purchase_order_product_recommendation-13.0.1.1.0.dist-info/WHEEL
odoo13_addon_purchase_order_product_recommendation-13.0.1.1.0.dist-info/top_level.txt
odoo13_addon_purchase_order_product_recommendation-13.0.1.1.0.dist-info/RECORD
